pytextprep/__init__.py
pytextprep/extract_hashtags.py
pytextprep/extract_ngram.py
pytextprep/generate_cloud.py
pytextprep/pytextprep.py
pytextprep/remove_punct.py
pytextprep-1.0.7.dist-info/LICENSE
pytextprep-1.0.7.dist-info/WHEEL
pytextprep-1.0.7.dist-info/METADATA
pytextprep-1.0.7.dist-info/RECORD
