Metadata-Version: 2.1
Name: pytextprep
Version: 1.0.7
Summary: Performs pre-processing of tweets
License: MIT
Author: Arijeet Chatterjee, Joshua Sia, Melisa Maidana, Philson Chan
Requires-Python: >=3.9,<4.0
Classifier: License :: OSI Approved :: MIT License
Classifier: Programming Language :: Python :: 3
Classifier: Programming Language :: Python :: 3.10
Classifier: Programming Language :: Python :: 3.9
Requires-Dist: matplotlib (>=3.5.1,<4.0.0)
Requires-Dist: nltk (>=3.6.7,<4.0.0)
Requires-Dist: numpy (>=1.22.1,<2.0.0)
Requires-Dist: wordcloud (>=1.8.1,<2.0.0)
